phonopy/exception.py
phonopy/units.py
phonopy/version.py
phonopy/_version.py
phonopy/_phonopy.abi3.so
phonopy/__init__.py
phonopy/api_gruneisen.py
phonopy/api_qha.py
phonopy/utils.py
phonopy/api_phonopy.py
phonopy/py.typed
phonopy/file_IO.py
phonopy/physical_units.py
phonopy/harmonic/force_constants.py
phonopy/harmonic/derivative_dynmat.py
phonopy/harmonic/dynamical_matrix.py
phonopy/harmonic/dynmat_to_fc.py
phonopy/harmonic/displacement.py
phonopy/interface/fc_calculator.py
phonopy/interface/elk.py
phonopy/interface/pypolymlp.py
phonopy/interface/siesta.py
phonopy/interface/crystal.py
phonopy/interface/wien2k.py
phonopy/interface/alm.py
phonopy/interface/abinit.py
phonopy/interface/cp2k.py
phonopy/interface/mlp.py
phonopy/interface/dftbp.py
phonopy/interface/abacus.py
phonopy/interface/calculator.py
phonopy/interface/phonopy_yaml.py
phonopy/interface/pwmat.py
phonopy/interface/aims.py
phonopy/interface/symfc.py
phonopy/interface/castep.py
phonopy/interface/cif.py
phonopy/interface/fleur.py
phonopy/interface/turbomole.py
phonopy/interface/vasp.py
phonopy/interface/qlm.py
phonopy/interface/lammps.py
phonopy/interface/qe.py
phonopy/qha/eos.py
phonopy/qha/core.py
phonopy/qha/electron.py
phonopy/phonon/group_velocity.py
phonopy/phonon/random_displacements.py
phonopy/phonon/thermal_properties.py
phonopy/phonon/dos.py
phonopy/phonon/moment.py
phonopy/phonon/qpoints.py
phonopy/phonon/character_table.py
phonopy/phonon/thermal_displacement.py
phonopy/phonon/mesh.py
phonopy/phonon/irreps.py
phonopy/phonon/animation.py
phonopy/phonon/tetrahedron_mesh.py
phonopy/phonon/degeneracy.py
phonopy/phonon/band_structure.py
phonopy/phonon/modulation.py
phonopy/gruneisen/core.py
phonopy/gruneisen/mesh.py
phonopy/gruneisen/band_structure.py
phonopy/scripts/phonopy_vasp_born.py
phonopy/scripts/phonopy_gruneisenplot.py
phonopy/scripts/phonopy_gruneisen.py
phonopy/scripts/phonopy_calc_convert.py
phonopy-2.47.1.dist-info/RECORD
phonopy-2.47.1.dist-info/WHEEL
phonopy-2.47.1.dist-info/entry_points.txt
phonopy-2.47.1.dist-info/METADATA
phonopy-2.47.1.dist-info/licenses/LICENSE
