Metadata-Version: 2.4
Name: phonopy
Version: 2.47.1
Summary: This is the phonopy module.
Author-Email: Atsushi Togo <atz.togo@gmail.com>
License-Expression: BSD-3-Clause
License-File: LICENSE
Project-URL: Homepage, https://phonopy.github.io/phonopy/
Project-URL: Repository, https://github.com/phonopy/phonopy
Requires-Python: >=3.10
Requires-Dist: numpy>=1.17.0
Requires-Dist: PyYAML>=5.3
Requires-Dist: matplotlib>=2.2.2
Requires-Dist: h5py>=3.0
Requires-Dist: spglib>=2.5
Requires-Dist: symfc>=1.5
Provides-Extra: cp2k
Requires-Dist: cp2k-input-tools; extra == "cp2k"
Provides-Extra: seekpath
Requires-Dist: seekpath; extra == "seekpath"
Provides-Extra: pypolymlp
Requires-Dist: pypolymlp>=0.10.0; extra == "pypolymlp"
Provides-Extra: tools
Requires-Dist: seekpath; extra == "tools"
Requires-Dist: pypolymlp>=0.10.0; extra == "tools"
